setup.py
thumbor_rackspace/__init__.py
thumbor_rackspace.egg-info/PKG-INFO
thumbor_rackspace.egg-info/SOURCES.txt
thumbor_rackspace.egg-info/dependency_links.txt
thumbor_rackspace.egg-info/top_level.txt
thumbor_rackspace/result_storages/__init__.py
thumbor_rackspace/result_storages/cloudfile_storage.py