Metadata-Version: 1.1
Name: thumbor-rackspace
Version: 0.1
Summary: Rackspace addons for Thumbor
Home-page: https://github.com/CodingNinja/thumbor_rackspace
Author: David Mann
Author-email: ninja@codingninja.com.au
License: MIT
Keywords: thumbor,rackspace,images,cloud
Platform: UNKNOWN
Classifier: Development Status :: 4 - Beta
Classifier: Intended Audience :: Developers
Classifier: License :: OSI Approved :: MIT License
Classifier: Natural Language :: English
Classifier: Operating System :: POSIX :: Linux
Classifier: Programming Language :: Python :: 2.6
Classifier: Topic :: Internet :: WWW/HTTP :: Dynamic Content
Classifier: Topic :: Multimedia :: Graphics :: Presentation
Requires: thumbor
Requires: pyrax
